numerox/__init__.py
numerox/data.py
numerox/metrics.py
numerox/model.py
numerox/numerai.py
numerox/prediction.py
numerox/run.py
numerox/splitter.py
numerox/testing.py
numerox/tokens.py
numerox/tournament.py
numerox/util.py
numerox/version.py
numerox/examples/__init__.py
numerox/examples/backtest.py
numerox/examples/concordance.py
numerox/examples/cv_warning.py
numerox/examples/improve_model.py
numerox/examples/production.py
numerox/examples/run_all_examples.py
numerox/tests/__init__.py
numerox/tests/test_data.hdf
numerox/tests/test_data.py
numerox/tests/test_examples.py
numerox/tests/test_metrics.py
numerox/tests/test_model.py
numerox/tests/test_numerai.py
numerox/tests/test_prediction.py
numerox/tests/test_run.py
numerox/tests/test_splitter.py
numerox/tests/test_tournament.py
numerox/tests/test_util.py
numerox/tests/tiny_dataset_csv.zip
numerox-4.1.6.dist-info/LICENSE
numerox-4.1.6.dist-info/METADATA
numerox-4.1.6.dist-info/WHEEL
numerox-4.1.6.dist-info/top_level.txt
numerox-4.1.6.dist-info/RECORD
