Metadata-Version: 2.1
Name: numerox
Version: 4.1.6
Summary: Numerai tournament toolbox written in Python
Home-page: https://github.com/numerai/numerox
Maintainer: Keith Goodman
License: GNU General Public License v3
Platform: OS Independent
Classifier: Development Status :: 4 - Beta
Classifier: Environment :: Console
Classifier: Intended Audience :: Science/Research
Classifier: License :: OSI Approved :: GNU General Public License v3 or later (GPLv3+)
Classifier: Operating System :: OS Independent
Classifier: Programming Language :: Python :: 3
Classifier: Topic :: Scientific/Engineering
Requires-Dist: numpy
Requires-Dist: scipy
Requires-Dist: pandas
Requires-Dist: tables
Requires-Dist: scikit-learn
Requires-Dist: numerapi (>=2.2.4)
Requires-Dist: nose
